binder/environment.yml
ci/environment-core-deps.yml
ci/environment-upstream-dev.yml
ci/environment.yml
doc/.gitignore
doc/Makefile
doc/api.rst
doc/boundary_conditions.rst
doc/conf.py
doc/contributor_guide.rst
doc/environment.yml
doc/grid_metrics.ipynb
doc/grid_topology.rst
doc/grid_ufuncs.rst
doc/grids.rst
doc/index.rst
doc/installation.rst
doc/make.bat
doc/transform.ipynb
doc/ufunc_examples.rst
doc/whats-new.rst
doc/images/axis_positions.svg
doc/images/cubed_sphere.jpeg
doc/images/cubed_sphere_face_connections.png
doc/images/grid2d_hv.png
doc/images/grid2d_hv.svg
doc/images/logo.png
doc/images/parallelize_broadcast.png
doc/images/parallelize_core.png
doc/images/two_faces.png
xgcm/__init__.py
xgcm/_version.py
xgcm/axis.py
xgcm/comodo.py
xgcm/grid.py
xgcm/grid_ufunc.py
xgcm/gridops.py
xgcm/metadata_parsers.py
xgcm/metrics.py
xgcm/padding.py
xgcm/regridding.py
xgcm/sgrid.py
xgcm/transform.py
xgcm/test/__init__.py
xgcm/test/datasets.py
xgcm/test/test_axis.py
xgcm/test/test_faceconnections.py
xgcm/test/test_grid.py
xgcm/test/test_grid_ufunc.py
xgcm/test/test_metadata_parsers.py
xgcm/test/test_metrics.py
xgcm/test/test_metrics_ops.py
xgcm/test/test_padding.py
xgcm/test/test_transform.py
xgcm-0.9.0.dist-info/licenses/LICENSE
xgcm-0.9.0.dist-info/METADATA
xgcm-0.9.0.dist-info/WHEEL
xgcm-0.9.0.dist-info/top_level.txt
xgcm-0.9.0.dist-info/RECORD
