Metadata-Version: 2.4
Name: xgcm
Version: 0.9.0
Summary: General Circulation Model Postprocessing with xarray
Author-email: xgcm Developers <julius@ldeo.columbia.edu>
License: MIT
Project-URL: Homepage, https://github.com/xgcm/xgcm
Project-URL: Tracker, https://github.com/xgcm/xgcm/issues
Keywords: pangeo,simulations,grids
Classifier: Development Status :: 5 - Production/Stable
Classifier: Intended Audience :: Science/Research
Classifier: Topic :: Scientific/Engineering
Classifier: License :: OSI Approved :: MIT License
Classifier: Operating System :: OS Independent
Classifier: Programming Language :: Python
Classifier: Programming Language :: Python :: 3.9
Classifier: Programming Language :: Python :: 3.10
Classifier: Programming Language :: Python :: 3.11
Requires-Python: >=3.9
License-File: LICENSE
Requires-Dist: xarray>=0.20.0
Requires-Dist: dask
Requires-Dist: numpy
Requires-Dist: future
Provides-Extra: dev
Requires-Dist: pytest; extra == "dev"
Requires-Dist: pytest-cov; extra == "dev"
Requires-Dist: scipy; extra == "dev"
Requires-Dist: flake8; extra == "dev"
Requires-Dist: black; extra == "dev"
Requires-Dist: codecov; extra == "dev"
Dynamic: license-file
